{
  "_meta": {
    "updated_at": "2026-04-20T08:24:56.840Z",
    "source": "GitHub Actions / fetch_current.js"
  },
  "gram-altin": {
    "name": "Gram Altın",
    "code": "GRAM",
    "type": "gold",
    "current": 6911.5,
    "selling": 6911.5,
    "buying": 6910.65,
    "change": -0.79
  },
  "ons": {
    "name": "Ons Altın",
    "code": "ONS",
    "type": "gold",
    "current": 214983.13,
    "selling": 214983.13,
    "buying": 214956.65,
    "change": -0.83
  },
  "ceyrek-altin": {
    "name": "Çeyrek Altın",
    "code": "CEYREK",
    "type": "gold",
    "current": 11366.07,
    "selling": 11366.07,
    "buying": 11113.08,
    "change": 0
  },
  "yarim-altin": {
    "name": "Yarım Altın",
    "code": "YARIM",
    "type": "gold",
    "current": 22732.14,
    "selling": 22732.14,
    "buying": 22156.69,
    "change": 0
  },
  "tam-altin": {
    "name": "Tam Altın",
    "code": "TAM",
    "type": "gold",
    "current": 45325.24,
    "selling": 45325.24,
    "buying": 44452.3,
    "change": 0
  },
  "cumhuriyet-altini": {
    "name": "Cumhuriyet Altını",
    "code": "CUMHUR",
    "type": "gold",
    "current": 46754,
    "selling": 46754,
    "buying": 46060,
    "change": -1.14
  },
  "ata-altin": {
    "name": "Ata Altın",
    "code": "ATAALT",
    "type": "gold",
    "current": 46993.65,
    "selling": 46993.65,
    "buying": 45841.44,
    "change": 0
  },
  "resat-altin": {
    "name": "Reşat Altın",
    "code": "RESAT",
    "type": "gold",
    "current": 46993.65,
    "selling": 46993.65,
    "buying": 45841.44,
    "change": 0
  },
  "hamit-altin": {
    "name": "Hamit Altın",
    "code": "HAMIT",
    "type": "gold",
    "current": 46993.65,
    "selling": 46993.65,
    "buying": 45841.44,
    "change": 0
  },
  "gram-has-altin": {
    "name": "Gram Has Altın",
    "code": "HAS",
    "type": "gold",
    "current": 6876.94,
    "selling": 6876.94,
    "buying": 6876.09,
    "change": -0.79
  },
  "14-ayar-altin": {
    "name": "14 Ayar Altın",
    "code": "14AYAR",
    "type": "gold",
    "current": 3962.48,
    "selling": 3962.48,
    "buying": 3959.03,
    "change": 0
  },
  "18-ayar-altin": {
    "name": "18 Ayar Altın",
    "code": "18AYAR",
    "type": "gold",
    "current": 5074.76,
    "selling": 5074.76,
    "buying": 5070.34,
    "change": 0
  },
  "22-ayar-bilezik": {
    "name": "22 Ayar Bilezik",
    "code": "22AYAR",
    "type": "gold",
    "current": 6339.97,
    "selling": 6339.97,
    "buying": 6334.45,
    "change": 0
  },
  "gumus": {
    "name": "Gümüş",
    "code": "GUMUS",
    "type": "commodity",
    "current": 114.55,
    "selling": 114.55,
    "buying": 114.48,
    "change": -1.67
  },
  "gram-platin": {
    "name": "Gram Platin",
    "code": "PLATIN",
    "type": "commodity",
    "current": 3007.28,
    "selling": 3007.28,
    "buying": 3000.04,
    "change": -1.52
  },
  "USD": {
    "name": "ABD Doları",
    "code": "USD",
    "type": "currency",
    "current": 44.881,
    "selling": 44.881,
    "buying": 44.8762,
    "change": 0.05
  },
  "EUR": {
    "name": "Euro",
    "code": "EUR",
    "type": "currency",
    "current": 52.8368,
    "selling": 52.8368,
    "buying": 52.8134,
    "change": 0.01
  },
  "GBP": {
    "name": "İngiliz Sterlini",
    "code": "GBP",
    "type": "currency",
    "current": 60.6494,
    "selling": 60.6494,
    "buying": 60.6275,
    "change": -0.06
  },
  "CHF": {
    "name": "İsviçre Frangı",
    "code": "CHF",
    "type": "currency",
    "current": 57.4124,
    "selling": 57.4124,
    "buying": 57.3887,
    "change": 0.01
  },
  "CAD": {
    "name": "Kanada Doları",
    "code": "CAD",
    "type": "currency",
    "current": 32.7862,
    "selling": 32.7862,
    "buying": 32.7755,
    "change": 0.04
  },
  "RUB": {
    "name": "Rus Rublesi",
    "code": "RUB",
    "type": "currency",
    "current": 0.5958,
    "selling": 0.5958,
    "buying": 0.5931,
    "change": 0.65
  },
  "AED": {
    "name": "BAE Dirhemi",
    "code": "AED",
    "type": "currency",
    "current": 12.2246,
    "selling": 12.2246,
    "buying": 12.2158,
    "change": 0.05
  },
  "AUD": {
    "name": "Avustralya Doları",
    "code": "AUD",
    "type": "currency",
    "current": 32.1022,
    "selling": 32.1022,
    "buying": 32.0923,
    "change": -0.21
  },
  "DKK": {
    "name": "DKK",
    "code": "DKK",
    "type": "currency",
    "current": 7.0643,
    "selling": 7.0643,
    "buying": 7.0621,
    "change": 0.02
  },
  "SEK": {
    "name": "SEK",
    "code": "SEK",
    "type": "currency",
    "current": 4.8959,
    "selling": 4.8959,
    "buying": 4.8934,
    "change": -0.01
  },
  "NOK": {
    "name": "NOK",
    "code": "NOK",
    "type": "currency",
    "current": 4.8022,
    "selling": 4.8022,
    "buying": 4.7995,
    "change": 0.34
  },
  "JPY": {
    "name": "Japon Yeni",
    "code": "JPY",
    "type": "currency",
    "current": 0.2829,
    "selling": 0.2829,
    "buying": 0.2822,
    "change": -0.18
  },
  "KWD": {
    "name": "Kuveyt Dinarı",
    "code": "KWD",
    "type": "currency",
    "current": 145.7438,
    "selling": 145.7438,
    "buying": 145.2487,
    "change": 0.03
  },
  "ZAR": {
    "name": "ZAR",
    "code": "ZAR",
    "type": "currency",
    "current": 2.7396,
    "selling": 2.7396,
    "buying": 2.7388,
    "change": -0.38
  },
  "BHD": {
    "name": "BHD",
    "code": "BHD",
    "type": "currency",
    "current": 118.9941,
    "selling": 118.9941,
    "buying": 118.9814,
    "change": 0.02
  },
  "LYD": {
    "name": "LYD",
    "code": "LYD",
    "type": "currency",
    "current": 7.1014,
    "selling": 7.1014,
    "buying": 7.1007,
    "change": 0.08
  },
  "SAR": {
    "name": "Suudi Riyali",
    "code": "SAR",
    "type": "currency",
    "current": 11.9783,
    "selling": 11.9783,
    "buying": 11.9494,
    "change": 0.05
  },
  "IQD": {
    "name": "IQD",
    "code": "IQD",
    "type": "currency",
    "current": 0.0341,
    "selling": 0.0341,
    "buying": 0.0341,
    "change": -0.29
  },
  "ILS": {
    "name": "İsrail Şekeli",
    "code": "ILS",
    "type": "currency",
    "current": 14.9568,
    "selling": 14.9568,
    "buying": 14.9552,
    "change": -0.08
  },
  "INR": {
    "name": "INR",
    "code": "INR",
    "type": "currency",
    "current": 0.4827,
    "selling": 0.4827,
    "buying": 0.4827,
    "change": 0.13
  },
  "MXN": {
    "name": "MXN",
    "code": "MXN",
    "type": "currency",
    "current": 2.5862,
    "selling": 2.5862,
    "buying": 2.5859,
    "change": -0.19
  },
  "HUF": {
    "name": "HUF",
    "code": "HUF",
    "type": "currency",
    "current": 0.1458,
    "selling": 0.1458,
    "buying": 0.1457,
    "change": -0.18
  },
  "NZD": {
    "name": "NZD",
    "code": "NZD",
    "type": "currency",
    "current": 26.3556,
    "selling": 26.3556,
    "buying": 26.3528,
    "change": -0.1
  },
  "BRL": {
    "name": "BRL",
    "code": "BRL",
    "type": "currency",
    "current": 9.0164,
    "selling": 9.0164,
    "buying": 9.0154,
    "change": 0.07
  },
  "IDR": {
    "name": "IDR",
    "code": "IDR",
    "type": "currency",
    "current": 0.0026,
    "selling": 0.0026,
    "buying": 0.0026,
    "change": -0.19
  },
  "CZK": {
    "name": "CZK",
    "code": "CZK",
    "type": "currency",
    "current": 2.1724,
    "selling": 2.1724,
    "buying": 2.1722,
    "change": -0.04
  },
  "PLN": {
    "name": "PLN",
    "code": "PLN",
    "type": "currency",
    "current": 12.469,
    "selling": 12.469,
    "buying": 12.4677,
    "change": -0.14
  },
  "RON": {
    "name": "RON",
    "code": "RON",
    "type": "currency",
    "current": 10.3557,
    "selling": 10.3557,
    "buying": 10.3484,
    "change": -0.02
  },
  "CNY": {
    "name": "CNY",
    "code": "CNY",
    "type": "currency",
    "current": 6.5821,
    "selling": 6.5821,
    "buying": 6.5811,
    "change": 0.01
  },
  "ARS": {
    "name": "ARS",
    "code": "ARS",
    "type": "currency",
    "current": 0.0329,
    "selling": 0.0329,
    "buying": 0.0329,
    "change": 0.05
  },
  "ALL": {
    "name": "ALL",
    "code": "ALL",
    "type": "currency",
    "current": 0.5523,
    "selling": 0.5523,
    "buying": 0.5523,
    "change": 0.13
  },
  "AZN": {
    "name": "Azerbaycan Manatı",
    "code": "AZN",
    "type": "currency",
    "current": 26.4006,
    "selling": 26.4006,
    "buying": 26.3978,
    "change": 0.05
  },
  "BAM": {
    "name": "BAM",
    "code": "BAM",
    "type": "currency",
    "current": 27.0677,
    "selling": 27.0677,
    "buying": 27.0648,
    "change": 0.13
  },
  "CLP": {
    "name": "CLP",
    "code": "CLP",
    "type": "currency",
    "current": 0.051,
    "selling": 0.051,
    "buying": 0.051,
    "change": 0.95
  },
  "COP": {
    "name": "COP",
    "code": "COP",
    "type": "currency",
    "current": 0.0125,
    "selling": 0.0125,
    "buying": 0.0125,
    "change": 0.25
  },
  "CRC": {
    "name": "CRC",
    "code": "CRC",
    "type": "currency",
    "current": 0.0985,
    "selling": 0.0985,
    "buying": 0.0985,
    "change": 0.01
  },
  "DZD": {
    "name": "DZD",
    "code": "DZD",
    "type": "currency",
    "current": 0.3393,
    "selling": 0.3393,
    "buying": 0.3392,
    "change": -0.03
  },
  "EGP": {
    "name": "EGP",
    "code": "EGP",
    "type": "currency",
    "current": 0.8674,
    "selling": 0.8674,
    "buying": 0.8673,
    "change": 0.12
  },
  "HKD": {
    "name": "HKD",
    "code": "HKD",
    "type": "currency",
    "current": 5.7297,
    "selling": 5.7297,
    "buying": 5.729,
    "change": 0.03
  },
  "ISK": {
    "name": "ISK",
    "code": "ISK",
    "type": "currency",
    "current": 0.3675,
    "selling": 0.3675,
    "buying": 0.3675,
    "change": 0.14
  },
  "KRW": {
    "name": "KRW",
    "code": "KRW",
    "type": "currency",
    "current": 0.0305,
    "selling": 0.0305,
    "buying": 0.0305,
    "change": -0.38
  },
  "KZT": {
    "name": "KZT",
    "code": "KZT",
    "type": "currency",
    "current": 0.0956,
    "selling": 0.0956,
    "buying": 0.0956,
    "change": 0.28
  },
  "LBP": {
    "name": "LBP",
    "code": "LBP",
    "type": "currency",
    "current": 0.0005,
    "selling": 0.0005,
    "buying": 0.0005,
    "change": -0.37
  },
  "LKR": {
    "name": "LKR",
    "code": "LKR",
    "type": "currency",
    "current": 0.1418,
    "selling": 0.1418,
    "buying": 0.1418,
    "change": -0.15
  },
  "MAD": {
    "name": "MAD",
    "code": "MAD",
    "type": "currency",
    "current": 4.8548,
    "selling": 4.8548,
    "buying": 4.8543,
    "change": -0.04
  },
  "MDL": {
    "name": "MDL",
    "code": "MDL",
    "type": "currency",
    "current": 2.6202,
    "selling": 2.6202,
    "buying": 2.6199,
    "change": 0.05
  },
  "MKD": {
    "name": "MKD",
    "code": "MKD",
    "type": "currency",
    "current": 0.8562,
    "selling": 0.8562,
    "buying": 0.8561,
    "change": -0.07
  },
  "MYR": {
    "name": "MYR",
    "code": "MYR",
    "type": "currency",
    "current": 11.3514,
    "selling": 11.3514,
    "buying": 11.3501,
    "change": 0.02
  },
  "OMR": {
    "name": "OMR",
    "code": "OMR",
    "type": "currency",
    "current": 116.7256,
    "selling": 116.7256,
    "buying": 116.7131,
    "change": 0.05
  },
  "PEN": {
    "name": "PEN",
    "code": "PEN",
    "type": "currency",
    "current": 13.0052,
    "selling": 13.0052,
    "buying": 13.0038,
    "change": -0.39
  },
  "PHP": {
    "name": "PHP",
    "code": "PHP",
    "type": "currency",
    "current": 0.7487,
    "selling": 0.7487,
    "buying": 0.7487,
    "change": -0.48
  },
  "PKR": {
    "name": "PKR",
    "code": "PKR",
    "type": "currency",
    "current": 0.1612,
    "selling": 0.1612,
    "buying": 0.1596,
    "change": -0.31
  },
  "QAR": {
    "name": "Katar Riyali",
    "code": "QAR",
    "type": "currency",
    "current": 12.7132,
    "selling": 12.7132,
    "buying": 11.8547,
    "change": -0.15
  },
  "RSD": {
    "name": "RSD",
    "code": "RSD",
    "type": "currency",
    "current": 0.4506,
    "selling": 0.4506,
    "buying": 0.4496,
    "change": 0.02
  },
  "SGD": {
    "name": "SGD",
    "code": "SGD",
    "type": "currency",
    "current": 35.2838,
    "selling": 35.2838,
    "buying": 35.28,
    "change": -0.09
  },
  "SYP": {
    "name": "SYP",
    "code": "SYP",
    "type": "currency",
    "current": 0.3885,
    "selling": 0.3885,
    "buying": 0.3885,
    "change": 0.05
  },
  "THB": {
    "name": "THB",
    "code": "THB",
    "type": "currency",
    "current": 1.3981,
    "selling": 1.3981,
    "buying": 1.398,
    "change": -0.5
  },
  "TWD": {
    "name": "TWD",
    "code": "TWD",
    "type": "currency",
    "current": 1.4243,
    "selling": 1.4243,
    "buying": 1.4242,
    "change": -0.08
  },
  "UAH": {
    "name": "UAH",
    "code": "UAH",
    "type": "currency",
    "current": 1.018,
    "selling": 1.018,
    "buying": 1.0179,
    "change": 0.02
  },
  "UYU": {
    "name": "UYU",
    "code": "UYU",
    "type": "currency",
    "current": 1.1246,
    "selling": 1.1246,
    "buying": 1.1244,
    "change": -0.3
  },
  "GEL": {
    "name": "GEL",
    "code": "GEL",
    "type": "currency",
    "current": 16.6226,
    "selling": 16.6226,
    "buying": 16.6208,
    "change": -0.32
  },
  "TND": {
    "name": "TND",
    "code": "TND",
    "type": "currency",
    "current": 15.4177,
    "selling": 15.4177,
    "buying": 15.4161,
    "change": -1.46
  },
  "BGN": {
    "name": "BGN",
    "code": "BGN",
    "type": "currency",
    "current": 27.1964,
    "selling": 27.1964,
    "buying": 26.8822,
    "change": -0.1
  }
}