{
  "_meta": {
    "updated_at": "2026-04-03T06:02:07.354Z",
    "source": "GitHub Actions / fetch_current.js"
  },
  "gram-altin": {
    "name": "Gram Altın",
    "code": "GRAM",
    "type": "gold",
    "current": 6705.34,
    "selling": 6705.34,
    "buying": 6703.92,
    "change": 0.28
  },
  "ons": {
    "name": "Ons Altın",
    "code": "ONS",
    "type": "gold",
    "current": 208603.74,
    "selling": 208603.74,
    "buying": 4676.57,
    "change": -0.01
  },
  "ceyrek-altin": {
    "name": "Çeyrek Altın",
    "code": "CEYREK",
    "type": "gold",
    "current": 11041.45,
    "selling": 11041.45,
    "buying": 10785.94,
    "change": 0
  },
  "yarim-altin": {
    "name": "Yarım Altın",
    "code": "YARIM",
    "type": "gold",
    "current": 22082.91,
    "selling": 22082.91,
    "buying": 21504.46,
    "change": 0
  },
  "tam-altin": {
    "name": "Tam Altın",
    "code": "TAM",
    "type": "gold",
    "current": 44030.75,
    "selling": 44030.75,
    "buying": 43143.75,
    "change": 0
  },
  "cumhuriyet-altini": {
    "name": "Cumhuriyet Altını",
    "code": "CUMHUR",
    "type": "gold",
    "current": 45495,
    "selling": 45495,
    "buying": 44820,
    "change": -1.89
  },
  "ata-altin": {
    "name": "Ata Altın",
    "code": "ATAALT",
    "type": "gold",
    "current": 45651.52,
    "selling": 45651.52,
    "buying": 44491.99,
    "change": 0
  },
  "resat-altin": {
    "name": "Reşat Altın",
    "code": "RESAT",
    "type": "gold",
    "current": 45651.52,
    "selling": 45651.52,
    "buying": 44491.99,
    "change": 0
  },
  "hamit-altin": {
    "name": "Hamit Altın",
    "code": "HAMIT",
    "type": "gold",
    "current": 45651.52,
    "selling": 45651.52,
    "buying": 44491.99,
    "change": 0
  },
  "gram-has-altin": {
    "name": "Gram Has Altın",
    "code": "HAS",
    "type": "gold",
    "current": 6671.81,
    "selling": 6671.81,
    "buying": 6670.4,
    "change": 0.28
  },
  "14-ayar-altin": {
    "name": "14 Ayar Altın",
    "code": "14AYAR",
    "type": "gold",
    "current": 3849.31,
    "selling": 3849.31,
    "buying": 3842.49,
    "change": 0
  },
  "18-ayar-altin": {
    "name": "18 Ayar Altın",
    "code": "18AYAR",
    "type": "gold",
    "current": 4929.82,
    "selling": 4929.82,
    "buying": 4921.08,
    "change": 0
  },
  "22-ayar-bilezik": {
    "name": "22 Ayar Bilezik",
    "code": "22AYAR",
    "type": "gold",
    "current": 6158.9,
    "selling": 6158.9,
    "buying": 6147.98,
    "change": 0
  },
  "gumus": {
    "name": "Gümüş",
    "code": "GUMUS",
    "type": "commodity",
    "current": 104.73,
    "selling": 104.73,
    "buying": 104.62,
    "change": 0.28
  },
  "gram-platin": {
    "name": "Gram Platin",
    "code": "PLATIN",
    "type": "commodity",
    "current": 2864.36,
    "selling": 2864.36,
    "buying": 2845.86,
    "change": 0.26
  },
  "USD": {
    "name": "ABD Doları",
    "code": "USD",
    "type": "currency",
    "current": 44.5967,
    "selling": 44.5967,
    "buying": 44.5777,
    "change": 0.28
  },
  "EUR": {
    "name": "Euro",
    "code": "EUR",
    "type": "currency",
    "current": 51.6333,
    "selling": 51.6333,
    "buying": 51.4706,
    "change": -0.03
  },
  "GBP": {
    "name": "İngiliz Sterlini",
    "code": "GBP",
    "type": "currency",
    "current": 59.2207,
    "selling": 59.2207,
    "buying": 59.0213,
    "change": 0.02
  },
  "CHF": {
    "name": "İsviçre Frangı",
    "code": "CHF",
    "type": "currency",
    "current": 55.8638,
    "selling": 55.8638,
    "buying": 55.8207,
    "change": 0.34
  },
  "CAD": {
    "name": "Kanada Doları",
    "code": "CAD",
    "type": "currency",
    "current": 32.0379,
    "selling": 32.0379,
    "buying": 32.0173,
    "change": 0.29
  },
  "RUB": {
    "name": "Rus Rublesi",
    "code": "RUB",
    "type": "currency",
    "current": 0.5561,
    "selling": 0.5561,
    "buying": 0.5558,
    "change": 0.52
  },
  "AED": {
    "name": "BAE Dirhemi",
    "code": "AED",
    "type": "currency",
    "current": 12.1462,
    "selling": 12.1462,
    "buying": 12.1381,
    "change": 0.32
  },
  "AUD": {
    "name": "Avustralya Doları",
    "code": "AUD",
    "type": "currency",
    "current": 30.8137,
    "selling": 30.8137,
    "buying": 30.7933,
    "change": 0.27
  },
  "DKK": {
    "name": "DKK",
    "code": "DKK",
    "type": "currency",
    "current": 6.8871,
    "selling": 6.8871,
    "buying": 6.8821,
    "change": 0.28
  },
  "SEK": {
    "name": "SEK",
    "code": "SEK",
    "type": "currency",
    "current": 4.7299,
    "selling": 4.7299,
    "buying": 4.7261,
    "change": 0.28
  },
  "NOK": {
    "name": "NOK",
    "code": "NOK",
    "type": "currency",
    "current": 4.5827,
    "selling": 4.5827,
    "buying": 4.5791,
    "change": 0.28
  },
  "JPY": {
    "name": "Japon Yeni",
    "code": "JPY",
    "type": "currency",
    "current": 0.2801,
    "selling": 0.2801,
    "buying": 0.279,
    "change": 0.07
  },
  "KWD": {
    "name": "Kuveyt Dinarı",
    "code": "KWD",
    "type": "currency",
    "current": 144.4175,
    "selling": 144.4175,
    "buying": 143.3737,
    "change": 0.07
  },
  "ZAR": {
    "name": "ZAR",
    "code": "ZAR",
    "type": "currency",
    "current": 2.6321,
    "selling": 2.6321,
    "buying": 2.63,
    "change": 0.27
  },
  "BHD": {
    "name": "BHD",
    "code": "BHD",
    "type": "currency",
    "current": 118.1213,
    "selling": 118.1213,
    "buying": 118.071,
    "change": 0.28
  },
  "LYD": {
    "name": "LYD",
    "code": "LYD",
    "type": "currency",
    "current": 6.9791,
    "selling": 6.9791,
    "buying": 6.9762,
    "change": -0.03
  },
  "SAR": {
    "name": "Suudi Riyali",
    "code": "SAR",
    "type": "currency",
    "current": 11.8923,
    "selling": 11.8923,
    "buying": 11.8633,
    "change": 0.3
  },
  "IQD": {
    "name": "IQD",
    "code": "IQD",
    "type": "currency",
    "current": 0.0341,
    "selling": 0.0341,
    "buying": 0.0341,
    "change": 0.5
  },
  "ILS": {
    "name": "İsrail Şekeli",
    "code": "ILS",
    "type": "currency",
    "current": 14.2204,
    "selling": 14.2204,
    "buying": 14.2144,
    "change": 0.25
  },
  "INR": {
    "name": "INR",
    "code": "INR",
    "type": "currency",
    "current": 0.4812,
    "selling": 0.4812,
    "buying": 0.481,
    "change": 0.61
  },
  "MXN": {
    "name": "MXN",
    "code": "MXN",
    "type": "currency",
    "current": 2.4976,
    "selling": 2.4976,
    "buying": 2.4965,
    "change": 0.32
  },
  "HUF": {
    "name": "HUF",
    "code": "HUF",
    "type": "currency",
    "current": 0.1339,
    "selling": 0.1339,
    "buying": 0.1338,
    "change": 0.29
  },
  "NZD": {
    "name": "NZD",
    "code": "NZD",
    "type": "currency",
    "current": 25.462,
    "selling": 25.462,
    "buying": 25.4512,
    "change": 0.15
  },
  "BRL": {
    "name": "BRL",
    "code": "BRL",
    "type": "currency",
    "current": 8.6468,
    "selling": 8.6468,
    "buying": 8.6431,
    "change": 0.28
  },
  "IDR": {
    "name": "IDR",
    "code": "IDR",
    "type": "currency",
    "current": 0.0026,
    "selling": 0.0026,
    "buying": 0.0026,
    "change": 0.25
  },
  "CZK": {
    "name": "CZK",
    "code": "CZK",
    "type": "currency",
    "current": 2.0992,
    "selling": 2.0992,
    "buying": 2.0983,
    "change": 0.28
  },
  "PLN": {
    "name": "PLN",
    "code": "PLN",
    "type": "currency",
    "current": 12.0304,
    "selling": 12.0304,
    "buying": 12.0253,
    "change": 0.25
  },
  "RON": {
    "name": "RON",
    "code": "RON",
    "type": "currency",
    "current": 10.1015,
    "selling": 10.1015,
    "buying": 10.0862,
    "change": 0.28
  },
  "CNY": {
    "name": "CNY",
    "code": "CNY",
    "type": "currency",
    "current": 6.4788,
    "selling": 6.4788,
    "buying": 6.4756,
    "change": 0.37
  },
  "ARS": {
    "name": "ARS",
    "code": "ARS",
    "type": "currency",
    "current": 0.0321,
    "selling": 0.0321,
    "buying": 0.0321,
    "change": 0
  },
  "ALL": {
    "name": "ALL",
    "code": "ALL",
    "type": "currency",
    "current": 0.5368,
    "selling": 0.5368,
    "buying": 0.5366,
    "change": 0.28
  },
  "AZN": {
    "name": "Azerbaycan Manatı",
    "code": "AZN",
    "type": "currency",
    "current": 26.2334,
    "selling": 26.2334,
    "buying": 26.2222,
    "change": 0.28
  },
  "BAM": {
    "name": "BAM",
    "code": "BAM",
    "type": "currency",
    "current": 26.2472,
    "selling": 26.2472,
    "buying": 26.2361,
    "change": -0.87
  },
  "CLP": {
    "name": "CLP",
    "code": "CLP",
    "type": "currency",
    "current": 0.0485,
    "selling": 0.0485,
    "buying": 0.0485,
    "change": 0.24
  },
  "COP": {
    "name": "COP",
    "code": "COP",
    "type": "currency",
    "current": 0.0122,
    "selling": 0.0122,
    "buying": 0.0122,
    "change": 0.28
  },
  "CRC": {
    "name": "CRC",
    "code": "CRC",
    "type": "currency",
    "current": 0.0959,
    "selling": 0.0959,
    "buying": 0.0958,
    "change": 0.24
  },
  "DZD": {
    "name": "DZD",
    "code": "DZD",
    "type": "currency",
    "current": 0.3352,
    "selling": 0.3352,
    "buying": 0.335,
    "change": 0.22
  },
  "EGP": {
    "name": "EGP",
    "code": "EGP",
    "type": "currency",
    "current": 0.8218,
    "selling": 0.8218,
    "buying": 0.8214,
    "change": 0.32
  },
  "HKD": {
    "name": "HKD",
    "code": "HKD",
    "type": "currency",
    "current": 5.6897,
    "selling": 5.6897,
    "buying": 5.6872,
    "change": 0.28
  },
  "ISK": {
    "name": "ISK",
    "code": "ISK",
    "type": "currency",
    "current": 0.3562,
    "selling": 0.3562,
    "buying": 0.3561,
    "change": 0.24
  },
  "KRW": {
    "name": "KRW",
    "code": "KRW",
    "type": "currency",
    "current": 0.0296,
    "selling": 0.0296,
    "buying": 0.0296,
    "change": 0.47
  },
  "KZT": {
    "name": "KZT",
    "code": "KZT",
    "type": "currency",
    "current": 0.0944,
    "selling": 0.0944,
    "buying": 0.0944,
    "change": 0.31
  },
  "LBP": {
    "name": "LBP",
    "code": "LBP",
    "type": "currency",
    "current": 0.0005,
    "selling": 0.0005,
    "buying": 0.0005,
    "change": 0
  },
  "LKR": {
    "name": "LKR",
    "code": "LKR",
    "type": "currency",
    "current": 0.1414,
    "selling": 0.1414,
    "buying": 0.1413,
    "change": 0.26
  },
  "MAD": {
    "name": "MAD",
    "code": "MAD",
    "type": "currency",
    "current": 4.7639,
    "selling": 4.7639,
    "buying": 4.7619,
    "change": 0.31
  },
  "MDL": {
    "name": "MDL",
    "code": "MDL",
    "type": "currency",
    "current": 2.5382,
    "selling": 2.5382,
    "buying": 2.5371,
    "change": 0.28
  },
  "MKD": {
    "name": "MKD",
    "code": "MKD",
    "type": "currency",
    "current": 0.8402,
    "selling": 0.8402,
    "buying": 0.8398,
    "change": 0.28
  },
  "MYR": {
    "name": "MYR",
    "code": "MYR",
    "type": "currency",
    "current": 11.0577,
    "selling": 11.0577,
    "buying": 11.053,
    "change": 0.43
  },
  "OMR": {
    "name": "OMR",
    "code": "OMR",
    "type": "currency",
    "current": 115.9862,
    "selling": 115.9862,
    "buying": 115.9368,
    "change": 0.28
  },
  "PEN": {
    "name": "PEN",
    "code": "PEN",
    "type": "currency",
    "current": 12.9228,
    "selling": 12.9228,
    "buying": 12.9173,
    "change": 0.31
  },
  "PHP": {
    "name": "PHP",
    "code": "PHP",
    "type": "currency",
    "current": 0.7375,
    "selling": 0.7375,
    "buying": 0.7372,
    "change": -0.08
  },
  "PKR": {
    "name": "PKR",
    "code": "PKR",
    "type": "currency",
    "current": 0.161,
    "selling": 0.161,
    "buying": 0.1594,
    "change": 0.56
  },
  "QAR": {
    "name": "Katar Riyali",
    "code": "QAR",
    "type": "currency",
    "current": 12.712,
    "selling": 12.712,
    "buying": 11.8337,
    "change": 0.62
  },
  "RSD": {
    "name": "RSD",
    "code": "RSD",
    "type": "currency",
    "current": 0.44,
    "selling": 0.44,
    "buying": 0.4382,
    "change": -0.02
  },
  "SGD": {
    "name": "SGD",
    "code": "SGD",
    "type": "currency",
    "current": 34.6948,
    "selling": 34.6948,
    "buying": 34.68,
    "change": 0.3
  },
  "SYP": {
    "name": "SYP",
    "code": "SYP",
    "type": "currency",
    "current": 0.3861,
    "selling": 0.3861,
    "buying": 0.386,
    "change": 0.28
  },
  "THB": {
    "name": "THB",
    "code": "THB",
    "type": "currency",
    "current": 1.3665,
    "selling": 1.3665,
    "buying": 1.3659,
    "change": 0.26
  },
  "TWD": {
    "name": "TWD",
    "code": "TWD",
    "type": "currency",
    "current": 1.3954,
    "selling": 1.3954,
    "buying": 1.3948,
    "change": 0.25
  },
  "UAH": {
    "name": "UAH",
    "code": "UAH",
    "type": "currency",
    "current": 1.0191,
    "selling": 1.0191,
    "buying": 1.0187,
    "change": 0.31
  },
  "UYU": {
    "name": "UYU",
    "code": "UYU",
    "type": "currency",
    "current": 1.1039,
    "selling": 1.1039,
    "buying": 1.1034,
    "change": 0.53
  },
  "GEL": {
    "name": "GEL",
    "code": "GEL",
    "type": "currency",
    "current": 16.6096,
    "selling": 16.6096,
    "buying": 16.6025,
    "change": 1.03
  },
  "TND": {
    "name": "TND",
    "code": "TND",
    "type": "currency",
    "current": 15.1638,
    "selling": 15.1638,
    "buying": 15.1573,
    "change": -0.36
  },
  "BGN": {
    "name": "BGN",
    "code": "BGN",
    "type": "currency",
    "current": 26.5034,
    "selling": 26.5034,
    "buying": 26.1935,
    "change": -0.6
  }
}