{
  "_meta": {
    "updated_at": "2026-04-14T14:44:32.958Z",
    "last_midnight": null,
    "last_month_end": null,
    "last_year_end": null
  },
  "gram-altin": {
    "hourly": [
      6719.4,
      6691.83,
      6714.96,
      6787.57,
      6799.46,
      6805.33,
      6779.47,
      6773.91,
      6797.65,
      6775.63,
      6819.94,
      6804.33,
      6816.01,
      6815.42,
      6817.31,
      6846.42,
      6840.01,
      6854.7,
      6850.33,
      6876.41,
      6872.27,
      6872.27,
      6866.98,
      6895.14
    ],
    "daily": [
      6704.43
    ],
    "monthly": [],
    "yearly": []
  },
  "ons": {
    "hourly": [
      209075.93,
      208336.8,
      208916.18,
      211152.72,
      211492.65,
      211698.05,
      210887.36,
      210713.12,
      211461.15,
      210772.69,
      212142.72,
      211650.72,
      212032.77,
      212028.65,
      212280.49,
      212985.34,
      212831.38,
      213288.13,
      213117.43,
      213906.19,
      213786.73,
      213786.73,
      213618.56,
      214496.65
    ],
    "daily": [
      208776.81
    ],
    "monthly": [],
    "yearly": []
  },
  "ceyrek-altin": {
    "hourly": [
      11217.79,
      11217.79,
      11217.79,
      11217.79,
      11217.79,
      11217.79,
      11140.14,
      11122.96,
      11122.83,
      11122.83,
      11122.83,
      11122.83,
      11122.83,
      11122.83,
      11122.83,
      11122.83,
      11122.83,
      11122.83,
      11122.83,
      11122.83,
      11242.95,
      11242.95,
      11240.43,
      11255.12
    ],
    "daily": [
      11156.48
    ],
    "monthly": [],
    "yearly": []
  },
  "yarim-altin": {
    "hourly": [
      22435.58,
      22435.58,
      22435.58,
      22435.58,
      22435.58,
      22435.58,
      22280.28,
      22245.92,
      22245.66,
      22245.66,
      22245.66,
      22245.66,
      22245.66,
      22245.66,
      22245.66,
      22245.66,
      22245.66,
      22245.66,
      22245.66,
      22245.66,
      22485.9,
      22485.9,
      22480.86,
      22510.23
    ],
    "daily": [
      22312.97
    ],
    "monthly": [],
    "yearly": []
  },
  "tam-altin": {
    "hourly": [
      44733.94,
      44733.94,
      44733.94,
      44733.94,
      44733.94,
      44733.94,
      44424.29,
      44355.79,
      44355.27,
      44355.27,
      44355.27,
      44355.27,
      44355.27,
      44355.27,
      44355.27,
      44355.27,
      44355.27,
      44355.27,
      44355.27,
      44355.27,
      44834.26,
      44834.26,
      44824.23,
      44882.79
    ],
    "daily": [
      44489.47
    ],
    "monthly": [],
    "yearly": []
  },
  "cumhuriyet-altini": {
    "hourly": [
      46100,
      46100,
      46100,
      46100,
      46100,
      46100,
      45850,
      45810,
      45770,
      45770,
      45770,
      45770,
      45770,
      45770,
      45770,
      45770,
      45770,
      45770,
      45770,
      45770,
      46230,
      46230,
      46180,
      46290
    ],
    "daily": [
      45857
    ],
    "monthly": [],
    "yearly": []
  },
  "ata-altin": {
    "hourly": [
      46380.59,
      46380.59,
      46380.59,
      46380.59,
      46380.59,
      46380.59,
      46059.54,
      45988.52,
      45987.98,
      45987.98,
      45987.98,
      45987.98,
      45987.98,
      45987.98,
      45987.98,
      45987.98,
      45987.98,
      45987.98,
      45987.98,
      45987.98,
      46484.61,
      46484.61,
      46474.2,
      46534.91
    ],
    "daily": [
      46127.12
    ],
    "monthly": [],
    "yearly": []
  },
  "resat-altin": {
    "hourly": [
      46380.59,
      46380.59,
      46380.59,
      46380.59,
      46380.59,
      46380.59,
      46059.54,
      45988.52,
      45987.98,
      45987.98,
      45987.98,
      45987.98,
      45987.98,
      45987.98,
      45987.98,
      45987.98,
      45987.98,
      45987.98,
      45987.98,
      45987.98,
      46484.61,
      46484.61,
      46474.2,
      46534.91
    ],
    "daily": [
      46127.12
    ],
    "monthly": [],
    "yearly": []
  },
  "hamit-altin": {
    "hourly": [
      46380.59,
      46380.59,
      46380.59,
      46380.59,
      46380.59,
      46380.59,
      46059.54,
      45988.52,
      45987.98,
      45987.98,
      45987.98,
      45987.98,
      45987.98,
      45987.98,
      45987.98,
      45987.98,
      45987.98,
      45987.98,
      45987.98,
      45987.98,
      46484.61,
      46484.61,
      46474.2,
      46534.91
    ],
    "daily": [
      46127.12
    ],
    "monthly": [],
    "yearly": []
  },
  "gram-has-altin": {
    "hourly": [
      6685.8,
      6658.37,
      6681.38,
      6753.63,
      6765.46,
      6771.3,
      6745.58,
      6740.04,
      6763.66,
      6741.75,
      6785.84,
      6770.31,
      6781.93,
      6781.34,
      6783.23,
      6812.19,
      6805.81,
      6820.42,
      6816.08,
      6842.02,
      6837.91,
      6837.91,
      6832.64,
      6860.67
    ],
    "daily": [
      6670.91
    ],
    "monthly": [],
    "yearly": []
  },
  "14-ayar-altin": {
    "hourly": [
      3910.79,
      3910.79,
      3910.79,
      3910.79,
      3910.79,
      3910.79,
      3883.72,
      3877.73,
      3877.68,
      3877.68,
      3877.68,
      3877.68,
      3877.68,
      3877.68,
      3877.68,
      3877.68,
      3877.68,
      3877.68,
      3877.68,
      3877.68,
      3919.56,
      3919.56,
      3918.68,
      3923.8
    ],
    "daily": [
      3889.42
    ],
    "monthly": [],
    "yearly": []
  },
  "18-ayar-altin": {
    "hourly": [
      5008.55,
      5008.55,
      5008.55,
      5008.55,
      5008.55,
      5008.55,
      4973.88,
      4966.22,
      4966.16,
      4966.16,
      4966.16,
      4966.16,
      4966.16,
      4966.16,
      4966.16,
      4966.16,
      4966.16,
      4966.16,
      4966.16,
      4966.16,
      5019.79,
      5019.79,
      5018.66,
      5025.22
    ],
    "daily": [
      4981.18
    ],
    "monthly": [],
    "yearly": []
  },
  "22-ayar-bilezik": {
    "hourly": [
      6257.26,
      6257.26,
      6257.26,
      6257.26,
      6257.26,
      6257.26,
      6213.95,
      6204.37,
      6204.29,
      6204.29,
      6204.29,
      6204.29,
      6204.29,
      6204.29,
      6204.29,
      6204.29,
      6204.29,
      6204.29,
      6204.29,
      6204.29,
      6271.3,
      6271.3,
      6269.89,
      6278.08
    ],
    "daily": [
      6223.07
    ],
    "monthly": [],
    "yearly": []
  },
  "gumus": {
    "hourly": [
      105.36,
      105.45,
      106.09,
      107.13,
      107.41,
      107.43,
      106.97,
      106.31,
      106.9,
      106.57,
      108.44,
      108.27,
      108.49,
      108.68,
      108.71,
      109.1,
      108.88,
      110.33,
      110.72,
      111.51,
      111.91,
      111.91,
      111.58,
      112.67
    ],
    "daily": [
      104.72
    ],
    "monthly": [],
    "yearly": []
  },
  "gram-platin": {
    "hourly": [
      2898.35,
      2884.22,
      2895.53,
      2947.17,
      2956.47,
      2954.37,
      2934.06,
      2915.2,
      2931.42,
      2945.87,
      2976.33,
      2978.75,
      2983.54,
      2988.55,
      2989.38,
      2995.78,
      3000.88,
      2997.77,
      2998.35,
      3020.54,
      3001.92,
      3001.92,
      2999.32,
      3006.02
    ],
    "daily": [
      2863.97
    ],
    "monthly": [],
    "yearly": []
  },
  "USD": {
    "hourly": [
      44.7,
      44.72,
      44.72,
      44.71,
      44.72,
      44.73,
      44.73,
      44.72,
      44.73,
      44.72,
      44.72,
      44.71,
      44.71,
      44.71,
      44.76,
      44.72,
      44.73,
      44.72,
      44.73,
      44.73,
      44.74,
      44.74,
      44.74,
      44.73
    ],
    "daily": [
      44.63
    ],
    "monthly": [],
    "yearly": []
  },
  "EUR": {
    "hourly": [
      52.25,
      52.23,
      52.27,
      52.34,
      52.32,
      52.34,
      52.31,
      52.3,
      52.4,
      52.41,
      52.52,
      52.58,
      52.62,
      52.63,
      52.65,
      52.65,
      52.69,
      52.66,
      52.66,
      52.72,
      52.78,
      52.78,
      52.82,
      52.81
    ],
    "daily": [
      51.6
    ],
    "monthly": [],
    "yearly": []
  },
  "GBP": {
    "hourly": [
      60.3,
      60.3,
      60.3,
      60.03,
      60.02,
      60.1,
      60.11,
      60.09,
      60.22,
      60.23,
      60.37,
      60.41,
      60.44,
      60.48,
      60.87,
      60.82,
      60.54,
      60.51,
      60.49,
      60.53,
      60.63,
      60.63,
      60.76,
      60.79
    ],
    "daily": [
      59.16
    ],
    "monthly": [],
    "yearly": []
  },
  "CHF": {
    "hourly": [
      56.46,
      56.38,
      56.42,
      56.48,
      56.47,
      56.62,
      56.6,
      56.59,
      56.75,
      56.79,
      56.96,
      57.05,
      57.06,
      57.04,
      57.14,
      57.1,
      57.12,
      57.08,
      57.09,
      57.19,
      57.32,
      57.32,
      57.34,
      57.31
    ],
    "daily": [
      55.85
    ],
    "monthly": [],
    "yearly": []
  },
  "CAD": {
    "hourly": [
      32.23,
      32.22,
      32.23,
      32.26,
      32.26,
      32.3,
      32.31,
      32.3,
      32.36,
      32.38,
      32.41,
      32.42,
      32.43,
      32.42,
      32.46,
      32.44,
      32.45,
      32.45,
      32.44,
      32.47,
      32.51,
      32.51,
      32.54,
      32.55
    ],
    "daily": [
      32.01
    ],
    "monthly": [],
    "yearly": []
  },
  "RUB": {
    "hourly": [
      0.58,
      0.58,
      0.58,
      0.58,
      0.58,
      0.59,
      0.59,
      0.59,
      0.59,
      0.59,
      0.59,
      0.59,
      0.59,
      0.59,
      0.59,
      0.59,
      0.59,
      0.59,
      0.59,
      0.59,
      0.6,
      0.6,
      0.59,
      0.59
    ],
    "daily": [
      0.56
    ],
    "monthly": [],
    "yearly": []
  },
  "AED": {
    "hourly": [
      12.18,
      12.18,
      12.18,
      12.18,
      12.18,
      12.18,
      12.18,
      12.18,
      12.18,
      12.18,
      12.17,
      12.17,
      12.17,
      12.17,
      12.19,
      12.18,
      12.18,
      12.18,
      12.18,
      12.18,
      12.19,
      12.19,
      12.19,
      12.18
    ],
    "daily": [
      12.14
    ],
    "monthly": [],
    "yearly": []
  },
  "AUD": {
    "hourly": [
      31.36,
      31.4,
      31.39,
      31.47,
      31.48,
      31.56,
      31.52,
      31.47,
      31.59,
      31.59,
      31.7,
      31.72,
      31.74,
      31.74,
      31.77,
      31.76,
      31.76,
      31.69,
      31.66,
      31.73,
      31.83,
      31.83,
      31.89,
      31.93
    ],
    "daily": [
      30.79
    ],
    "monthly": [],
    "yearly": []
  },
  "DKK": {
    "hourly": [
      6.99,
      6.99,
      6.99,
      6.99,
      7,
      7,
      7,
      7,
      7.01,
      7.01,
      7.02,
      7.03,
      7.04,
      7.04,
      7.04,
      7.04,
      7.04,
      7.04,
      7.04,
      7.05,
      7.06,
      7.06,
      7.07,
      7.06
    ],
    "daily": [
      6.88
    ],
    "monthly": [],
    "yearly": []
  },
  "SEK": {
    "hourly": [
      4.79,
      4.79,
      4.79,
      4.79,
      4.79,
      4.8,
      4.8,
      4.8,
      4.84,
      4.85,
      4.87,
      4.87,
      4.87,
      4.87,
      4.88,
      4.87,
      4.87,
      4.87,
      4.87,
      4.88,
      4.89,
      4.89,
      4.89,
      4.88
    ],
    "daily": [
      4.72
    ],
    "monthly": [],
    "yearly": []
  },
  "NOK": {
    "hourly": [
      4.68,
      4.69,
      4.69,
      4.69,
      4.7,
      4.72,
      4.71,
      4.71,
      4.72,
      4.72,
      4.73,
      4.73,
      4.73,
      4.74,
      4.75,
      4.73,
      4.74,
      4.73,
      4.74,
      4.74,
      4.75,
      4.75,
      4.76,
      4.75
    ],
    "daily": [
      4.58
    ],
    "monthly": [],
    "yearly": []
  },
  "JPY": {
    "hourly": [
      0.28,
      0.28,
      0.28,
      0.28,
      0.28,
      0.28,
      0.28,
      0.28,
      0.28,
      0.28,
      0.28,
      0.28,
      0.28,
      0.28,
      0.28,
      0.28,
      0.28,
      0.28,
      0.28,
      0.28,
      0.28,
      0.28,
      0.28,
      0.28
    ],
    "daily": [
      0.28
    ],
    "monthly": [],
    "yearly": []
  },
  "KWD": {
    "hourly": [
      144.95,
      144.95,
      144.95,
      144.95,
      144.94,
      144.99,
      144.98,
      144.96,
      145.02,
      145.01,
      145.06,
      145.08,
      145.88,
      145.01,
      145.18,
      145.11,
      145.11,
      145.08,
      145.06,
      144.96,
      145.02,
      145.02,
      145.02,
      145.09
    ],
    "daily": [
      144.42
    ],
    "monthly": [],
    "yearly": []
  },
  "ZAR": {
    "hourly": [
      2.69,
      2.69,
      2.7,
      2.7,
      2.7,
      2.71,
      2.71,
      2.7,
      2.71,
      2.71,
      2.72,
      2.73,
      2.73,
      2.72,
      2.73,
      2.73,
      2.73,
      2.73,
      2.72,
      2.73,
      2.74,
      2.74,
      2.74,
      2.74
    ],
    "daily": [
      2.63
    ],
    "monthly": [],
    "yearly": []
  },
  "BHD": {
    "hourly": [
      118.52,
      118.57,
      118.55,
      118.54,
      118.58,
      118.59,
      118.57,
      118.53,
      118.52,
      118.5,
      118.49,
      118.48,
      118.48,
      118.46,
      118.61,
      118.52,
      118.52,
      118.51,
      118.55,
      118.51,
      118.58,
      118.58,
      118.6,
      118.53
    ],
    "daily": [
      117.3
    ],
    "monthly": [],
    "yearly": []
  },
  "LYD": {
    "hourly": [
      7.03,
      7.04,
      7.04,
      7.04,
      7.04,
      7.02,
      7.02,
      7.04,
      7.04,
      7.05,
      7.05,
      7.04,
      7.04,
      7.03,
      7.04,
      7.04,
      7.04,
      7.04,
      7.04,
      7.04,
      7.04,
      7.04,
      7.06,
      7.06
    ],
    "daily": [
      6.98
    ],
    "monthly": [],
    "yearly": []
  },
  "SAR": {
    "hourly": [
      12.13,
      12.13,
      12.14,
      12.13,
      12.12,
      11.93,
      11.93,
      11.93,
      11.93,
      11.93,
      11.93,
      11.93,
      11.93,
      11.93,
      11.94,
      11.93,
      11.93,
      11.93,
      11.93,
      11.93,
      11.94,
      11.94,
      11.94,
      11.94
    ],
    "daily": [
      11.89
    ],
    "monthly": [],
    "yearly": []
  },
  "IQD": {
    "hourly": [
      0.03,
      0.03,
      0.03,
      0.03,
      0.03,
      0.03,
      0.03,
      0.03,
      0.03,
      0.03,
      0.03,
      0.03,
      0.03,
      0.03,
      0.03,
      0.03,
      0.03,
      0.03,
      0.03,
      0.03,
      0.03,
      0.03,
      0.03,
      0.03
    ],
    "daily": [
      0.03
    ],
    "monthly": [],
    "yearly": []
  },
  "ILS": {
    "hourly": [
      14.72,
      14.72,
      14.72,
      14.64,
      14.62,
      14.61,
      14.62,
      14.6,
      14.69,
      14.64,
      14.68,
      14.7,
      14.71,
      14.71,
      14.73,
      14.68,
      14.69,
      14.69,
      14.73,
      14.73,
      14.82,
      14.82,
      14.85,
      14.84
    ],
    "daily": [
      14.27
    ],
    "monthly": [],
    "yearly": []
  },
  "INR": {
    "hourly": [
      0.48,
      0.48,
      0.48,
      0.48,
      0.48,
      0.48,
      0.48,
      0.48,
      0.48,
      0.48,
      0.48,
      0.48,
      0.48,
      0.48,
      0.48,
      0.48,
      0.48,
      0.48,
      0.48,
      0.48,
      0.48,
      0.48,
      0.48,
      0.48
    ],
    "daily": [
      0.48
    ],
    "monthly": [],
    "yearly": []
  },
  "MXN": {
    "hourly": [
      2.57,
      2.57,
      2.56,
      2.57,
      2.57,
      2.57,
      2.58,
      2.57,
      2.58,
      2.58,
      2.58,
      2.58,
      2.58,
      2.58,
      2.59,
      2.59,
      2.59,
      2.58,
      2.58,
      2.59,
      2.59,
      2.59,
      2.6,
      2.59
    ],
    "daily": [
      2.5
    ],
    "monthly": [],
    "yearly": []
  },
  "HUF": {
    "hourly": [
      0.14,
      0.14,
      0.14,
      0.14,
      0.14,
      0.14,
      0.14,
      0.14,
      0.14,
      0.14,
      0.14,
      0.14,
      0.14,
      0.14,
      0.14,
      0.14,
      0.14,
      0.14,
      0.14,
      0.14,
      0.15,
      0.15,
      0.15,
      0.15
    ],
    "daily": [
      0.13
    ],
    "monthly": [],
    "yearly": []
  },
  "NZD": {
    "hourly": [
      25.93,
      25.94,
      25.95,
      26.04,
      26.05,
      26.09,
      26.07,
      26.03,
      26.12,
      26.12,
      26.2,
      26.24,
      26.24,
      26.23,
      26.25,
      26.26,
      26.26,
      26.23,
      26.25,
      26.31,
      26.38,
      26.38,
      26.41,
      26.43
    ],
    "daily": [
      25.4
    ],
    "monthly": [],
    "yearly": []
  },
  "BRL": {
    "hourly": [
      8.93,
      8.93,
      8.93,
      8.93,
      8.93,
      8.93,
      8.93,
      8.89,
      8.89,
      8.9,
      8.96,
      8.94,
      8.94,
      8.95,
      8.96,
      8.95,
      8.95,
      8.95,
      8.95,
      8.96,
      8.96,
      8.96,
      8.96,
      8.99
    ],
    "daily": [
      8.66
    ],
    "monthly": [],
    "yearly": []
  },
  "IDR": {
    "hourly": [
      0,
      0,
      0,
      0,
      0,
      0,
      0,
      0,
      0,
      0,
      0,
      0,
      0,
      0,
      0,
      0,
      0,
      0,
      0,
      0,
      0,
      0,
      0,
      0
    ],
    "daily": [
      0
    ],
    "monthly": [],
    "yearly": []
  },
  "CZK": {
    "hourly": [
      2.14,
      2.14,
      2.14,
      2.14,
      2.14,
      2.15,
      2.14,
      2.14,
      2.15,
      2.15,
      2.15,
      2.16,
      2.16,
      2.16,
      2.16,
      2.16,
      2.16,
      2.16,
      2.16,
      2.16,
      2.17,
      2.17,
      2.17,
      2.17
    ],
    "daily": [
      2.1
    ],
    "monthly": [],
    "yearly": []
  },
  "PLN": {
    "hourly": [
      12.34,
      12.34,
      12.34,
      12.28,
      12.29,
      12.31,
      12.29,
      12.29,
      12.32,
      12.33,
      12.37,
      12.38,
      12.39,
      12.39,
      12.39,
      12.38,
      12.39,
      12.39,
      12.39,
      12.42,
      12.43,
      12.43,
      12.44,
      12.44
    ],
    "daily": [
      12.02
    ],
    "monthly": [],
    "yearly": []
  },
  "RON": {
    "hourly": [
      10.27,
      10.26,
      10.26,
      10.27,
      10.27,
      10.28,
      10.27,
      10.27,
      10.29,
      10.29,
      10.32,
      10.33,
      10.34,
      10.34,
      10.35,
      10.35,
      10.36,
      10.35,
      10.35,
      10.35,
      10.36,
      10.36,
      10.37,
      10.37
    ],
    "daily": [
      10.09
    ],
    "monthly": [],
    "yearly": []
  },
  "CNY": {
    "hourly": [
      6.54,
      6.54,
      6.54,
      6.55,
      6.55,
      6.55,
      6.55,
      6.55,
      6.55,
      6.55,
      6.56,
      6.56,
      6.56,
      6.56,
      6.57,
      6.56,
      6.56,
      6.56,
      6.56,
      6.57,
      6.57,
      6.57,
      6.57,
      6.57
    ],
    "daily": [
      6.48
    ],
    "monthly": [],
    "yearly": []
  },
  "ARS": {
    "hourly": [
      0.03,
      0.03,
      0.03,
      0.03,
      0.03,
      0.03,
      0.03,
      0.03,
      0.03,
      0.03,
      0.03,
      0.03,
      0.03,
      0.03,
      0.03,
      0.03,
      0.03,
      0.03,
      0.03,
      0.03,
      0.03,
      0.03,
      0.03,
      0.03
    ],
    "daily": [
      0.03
    ],
    "monthly": [],
    "yearly": []
  },
  "ALL": {
    "hourly": [
      0.55,
      0.55,
      0.55,
      0.55,
      0.55,
      0.55,
      0.55,
      0.55,
      0.55,
      0.55,
      0.55,
      0.55,
      0.55,
      0.55,
      0.55,
      0.55,
      0.55,
      0.55,
      0.55,
      0.55,
      0.55,
      0.55,
      0.55,
      0.55
    ],
    "daily": [
      0.54
    ],
    "monthly": [],
    "yearly": []
  },
  "AZN": {
    "hourly": [
      26.3,
      26.31,
      26.3,
      26.3,
      26.31,
      26.31,
      26.31,
      26.31,
      26.31,
      26.31,
      26.3,
      26.3,
      26.3,
      26.3,
      26.33,
      26.3,
      26.31,
      26.31,
      26.31,
      26.31,
      26.32,
      26.32,
      26.32,
      26.31
    ],
    "daily": [
      26.26
    ],
    "monthly": [],
    "yearly": []
  },
  "BAM": {
    "hourly": [
      26.78,
      26.79,
      26.79,
      26.79,
      26.79,
      26.73,
      26.73,
      26.75,
      26.75,
      26.77,
      26.76,
      26.76,
      26.76,
      26.78,
      26.82,
      26.79,
      26.79,
      26.79,
      26.79,
      26.8,
      26.8,
      26.8,
      26.99,
      26.99
    ],
    "daily": [
      26.27
    ],
    "monthly": [],
    "yearly": []
  },
  "CLP": {
    "hourly": [
      0.05,
      0.05,
      0.05,
      0.05,
      0.05,
      0.05,
      0.05,
      0.05,
      0.05,
      0.05,
      0.05,
      0.05,
      0.05,
      0.05,
      0.05,
      0.05,
      0.05,
      0.05,
      0.05,
      0.05,
      0.05,
      0.05,
      0.05,
      0.05
    ],
    "daily": [
      0.05
    ],
    "monthly": [],
    "yearly": []
  },
  "COP": {
    "hourly": [
      0.01,
      0.01,
      0.01,
      0.01,
      0.01,
      0.01,
      0.01,
      0.01,
      0.01,
      0.01,
      0.01,
      0.01,
      0.01,
      0.01,
      0.01,
      0.01,
      0.01,
      0.01,
      0.01,
      0.01,
      0.01,
      0.01,
      0.01,
      0.01
    ],
    "daily": [
      0.01
    ],
    "monthly": [],
    "yearly": []
  },
  "CRC": {
    "hourly": [
      0.1,
      0.1,
      0.1,
      0.1,
      0.1,
      0.1,
      0.1,
      0.1,
      0.1,
      0.1,
      0.1,
      0.1,
      0.1,
      0.1,
      0.1,
      0.1,
      0.1,
      0.1,
      0.1,
      0.1,
      0.1,
      0.1,
      0.1,
      0.1
    ],
    "daily": [
      0.1
    ],
    "monthly": [],
    "yearly": []
  },
  "DZD": {
    "hourly": [
      0.34,
      0.34,
      0.34,
      0.34,
      0.34,
      0.34,
      0.34,
      0.34,
      0.34,
      0.34,
      0.34,
      0.34,
      0.34,
      0.34,
      0.34,
      0.34,
      0.34,
      0.34,
      0.34,
      0.34,
      0.34,
      0.34,
      0.34,
      0.34
    ],
    "daily": [
      0.34
    ],
    "monthly": [],
    "yearly": []
  },
  "EGP": {
    "hourly": [
      0.84,
      0.84,
      0.84,
      0.84,
      0.84,
      0.84,
      0.84,
      0.84,
      0.84,
      0.84,
      0.84,
      0.84,
      0.84,
      0.84,
      0.84,
      0.84,
      0.84,
      0.84,
      0.84,
      0.84,
      0.85,
      0.85,
      0.85,
      0.85
    ],
    "daily": [
      0.82
    ],
    "monthly": [],
    "yearly": []
  },
  "HKD": {
    "hourly": [
      5.71,
      5.71,
      5.71,
      5.71,
      5.71,
      5.71,
      5.71,
      5.71,
      5.71,
      5.71,
      5.71,
      5.71,
      5.71,
      5.71,
      5.72,
      5.71,
      5.71,
      5.71,
      5.71,
      5.71,
      5.71,
      5.71,
      5.71,
      5.71
    ],
    "daily": [
      5.7
    ],
    "monthly": [],
    "yearly": []
  },
  "ISK": {
    "hourly": [
      0.37,
      0.37,
      0.37,
      0.36,
      0.36,
      0.37,
      0.37,
      0.36,
      0.37,
      0.37,
      0.37,
      0.37,
      0.37,
      0.37,
      0.37,
      0.37,
      0.37,
      0.37,
      0.37,
      0.37,
      0.37,
      0.37,
      0.37,
      0.37
    ],
    "daily": [
      0.36
    ],
    "monthly": [],
    "yearly": []
  },
  "KRW": {
    "hourly": [
      0.03,
      0.03,
      0.03,
      0.03,
      0.03,
      0.03,
      0.03,
      0.03,
      0.03,
      0.03,
      0.03,
      0.03,
      0.03,
      0.03,
      0.03,
      0.03,
      0.03,
      0.03,
      0.03,
      0.03,
      0.03,
      0.03,
      0.03,
      0.03
    ],
    "daily": [
      0.03
    ],
    "monthly": [],
    "yearly": []
  },
  "KZT": {
    "hourly": [
      0.09,
      0.09,
      0.09,
      0.09,
      0.09,
      0.09,
      0.09,
      0.09,
      0.09,
      0.09,
      0.09,
      0.09,
      0.09,
      0.09,
      0.09,
      0.09,
      0.09,
      0.09,
      0.09,
      0.09,
      0.09,
      0.09,
      0.09,
      0.09
    ],
    "daily": [
      0.09
    ],
    "monthly": [],
    "yearly": []
  },
  "LBP": {
    "hourly": [
      0,
      0,
      0,
      0,
      0,
      0,
      0,
      0,
      0,
      0,
      0,
      0,
      0,
      0,
      0,
      0,
      0,
      0,
      0,
      0,
      0,
      0,
      0,
      0
    ],
    "daily": [
      0
    ],
    "monthly": [],
    "yearly": []
  },
  "LKR": {
    "hourly": [
      0.14,
      0.14,
      0.14,
      0.14,
      0.14,
      0.14,
      0.14,
      0.14,
      0.14,
      0.14,
      0.14,
      0.14,
      0.14,
      0.14,
      0.14,
      0.14,
      0.14,
      0.14,
      0.14,
      0.14,
      0.14,
      0.14,
      0.14,
      0.14
    ],
    "daily": [
      0.14
    ],
    "monthly": [],
    "yearly": []
  },
  "MAD": {
    "hourly": [
      4.82,
      4.82,
      4.82,
      4.83,
      4.83,
      4.81,
      4.81,
      4.81,
      4.81,
      4.81,
      4.82,
      4.83,
      4.83,
      4.83,
      4.83,
      4.83,
      4.83,
      4.83,
      4.83,
      4.83,
      4.84,
      4.84,
      4.84,
      4.84
    ],
    "daily": [
      4.75
    ],
    "monthly": [],
    "yearly": []
  },
  "MDL": {
    "hourly": [
      2.62,
      2.62,
      2.62,
      2.62,
      2.62,
      2.62,
      2.62,
      2.62,
      2.62,
      2.62,
      2.62,
      2.62,
      2.62,
      2.62,
      2.62,
      2.62,
      2.62,
      2.62,
      2.61,
      2.61,
      2.61,
      2.61,
      2.62,
      2.63
    ],
    "daily": [
      2.55
    ],
    "monthly": [],
    "yearly": []
  },
  "MKD": {
    "hourly": [
      0.84,
      0.84,
      0.84,
      0.84,
      0.84,
      0.84,
      0.84,
      0.84,
      0.84,
      0.84,
      0.84,
      0.84,
      0.84,
      0.84,
      0.84,
      0.84,
      0.84,
      0.84,
      0.84,
      0.84,
      0.84,
      0.84,
      0.84,
      0.84
    ],
    "daily": [
      0.83
    ],
    "monthly": [],
    "yearly": []
  },
  "MYR": {
    "hourly": [
      11.27,
      11.27,
      11.25,
      11.25,
      11.25,
      11.26,
      11.25,
      11.25,
      11.25,
      11.25,
      11.25,
      11.25,
      11.25,
      11.25,
      11.26,
      11.25,
      11.25,
      11.3,
      11.31,
      11.31,
      11.32,
      11.32,
      11.32,
      11.32
    ],
    "daily": [
      11.07
    ],
    "monthly": [],
    "yearly": []
  },
  "OMR": {
    "hourly": [
      116.3,
      116.35,
      116.33,
      116.32,
      116.3,
      116.32,
      116.33,
      116.32,
      116.32,
      116.32,
      116.29,
      116.29,
      116.29,
      116.31,
      116.41,
      116.31,
      116.33,
      116.32,
      116.32,
      116.33,
      116.37,
      116.37,
      116.36,
      116.34
    ],
    "daily": [
      116.08
    ],
    "monthly": [],
    "yearly": []
  },
  "PEN": {
    "hourly": [
      13.27,
      13.28,
      13.27,
      13.27,
      13.27,
      13.23,
      13.23,
      13.2,
      13.2,
      13.2,
      13.2,
      13.2,
      13.2,
      13.26,
      13.28,
      13.27,
      13.27,
      13.27,
      13.27,
      13.27,
      13.27,
      13.27,
      13.27,
      13.27
    ],
    "daily": [
      12.93
    ],
    "monthly": [],
    "yearly": []
  },
  "PHP": {
    "hourly": [
      0.75,
      0.75,
      0.75,
      0.74,
      0.74,
      0.74,
      0.74,
      0.74,
      0.74,
      0.74,
      0.74,
      0.74,
      0.75,
      0.75,
      0.75,
      0.74,
      0.74,
      0.75,
      0.75,
      0.75,
      0.75,
      0.75,
      0.75,
      0.75
    ],
    "daily": [
      0.74
    ],
    "monthly": [],
    "yearly": []
  },
  "PKR": {
    "hourly": [
      0.16,
      0.16,
      0.16,
      0.16,
      0.16,
      0.16,
      0.16,
      0.16,
      0.16,
      0.16,
      0.16,
      0.16,
      0.16,
      0.16,
      0.16,
      0.16,
      0.16,
      0.16,
      0.16,
      0.16,
      0.16,
      0.16,
      0.16,
      0.16
    ],
    "daily": [
      0.16
    ],
    "monthly": [],
    "yearly": []
  },
  "QAR": {
    "hourly": [
      12.73,
      12.73,
      12.73,
      12.73,
      12.73,
      12.69,
      12.69,
      12.72,
      12.72,
      12.73,
      12.73,
      12.73,
      12.72,
      12.26,
      12.28,
      12.27,
      12.27,
      12.27,
      12.27,
      12.27,
      12.27,
      12.27,
      12.72,
      12.72
    ],
    "daily": [
      12.71
    ],
    "monthly": [],
    "yearly": []
  },
  "RSD": {
    "hourly": [
      0.45,
      0.45,
      0.45,
      0.45,
      0.45,
      0.45,
      0.45,
      0.45,
      0.45,
      0.45,
      0.45,
      0.45,
      0.45,
      0.45,
      0.45,
      0.45,
      0.45,
      0.45,
      0.45,
      0.45,
      0.45,
      0.45,
      0.45,
      0.45
    ],
    "daily": [
      0.44
    ],
    "monthly": [],
    "yearly": []
  },
  "SGD": {
    "hourly": [
      34.99,
      34.99,
      35,
      35.04,
      35.04,
      35.07,
      35.06,
      35.04,
      35.09,
      35.08,
      35.12,
      35.13,
      35.13,
      35.12,
      35.17,
      35.15,
      35.16,
      35.12,
      35.12,
      35.15,
      35.18,
      35.18,
      35.2,
      35.2
    ],
    "daily": [
      34.67
    ],
    "monthly": [],
    "yearly": []
  },
  "SYP": {
    "hourly": [
      0.39,
      0.39,
      0.39,
      0.39,
      0.39,
      0.39,
      0.39,
      0.39,
      0.39,
      0.39,
      0.39,
      0.39,
      0.39,
      0.39,
      0.39,
      0.39,
      0.39,
      0.39,
      0.39,
      0.39,
      0.39,
      0.39,
      0.39,
      0.39
    ],
    "daily": [
      0.39
    ],
    "monthly": [],
    "yearly": []
  },
  "THB": {
    "hourly": [
      1.39,
      1.38,
      1.38,
      1.39,
      1.38,
      1.39,
      1.39,
      1.39,
      1.39,
      1.39,
      1.4,
      1.4,
      1.4,
      1.39,
      1.39,
      1.4,
      1.4,
      1.39,
      1.39,
      1.4,
      1.4,
      1.4,
      1.4,
      1.4
    ],
    "daily": [
      1.37
    ],
    "monthly": [],
    "yearly": []
  },
  "TWD": {
    "hourly": [
      1.41,
      1.41,
      1.41,
      1.41,
      1.41,
      1.41,
      1.41,
      1.41,
      1.41,
      1.41,
      1.41,
      1.41,
      1.41,
      1.41,
      1.41,
      1.41,
      1.41,
      1.41,
      1.41,
      1.41,
      1.42,
      1.42,
      1.42,
      1.42
    ],
    "daily": [
      1.4
    ],
    "monthly": [],
    "yearly": []
  },
  "UAH": {
    "hourly": [
      1.03,
      1.03,
      1.03,
      1.03,
      1.03,
      1.03,
      1.03,
      1.03,
      1.03,
      1.03,
      1.03,
      1.03,
      1.03,
      1.03,
      1.03,
      1.03,
      1.03,
      1.03,
      1.03,
      1.03,
      1.03,
      1.03,
      1.03,
      1.03
    ],
    "daily": [
      1.02
    ],
    "monthly": [],
    "yearly": []
  },
  "UYU": {
    "hourly": [
      1.11,
      1.11,
      1.11,
      1.11,
      1.11,
      1.11,
      1.11,
      1.11,
      1.11,
      1.11,
      1.11,
      1.11,
      1.11,
      1.11,
      1.11,
      1.11,
      1.11,
      1.11,
      1.11,
      1.11,
      1.11,
      1.11,
      1.11,
      1.11
    ],
    "daily": [
      1.1
    ],
    "monthly": [],
    "yearly": []
  },
  "GEL": {
    "hourly": [
      16.62,
      16.63,
      16.62,
      16.62,
      16.62,
      16.63,
      16.63,
      16.63,
      16.63,
      16.63,
      16.62,
      16.62,
      16.62,
      16.62,
      16.64,
      16.62,
      16.63,
      16.63,
      16.63,
      16.63,
      16.63,
      16.63,
      16.63,
      16.63
    ],
    "daily": [
      16.62
    ],
    "monthly": [],
    "yearly": []
  },
  "TND": {
    "hourly": [
      15.32,
      15.33,
      15.33,
      15.33,
      15.33,
      15.28,
      15.28,
      15.33,
      15.33,
      15.34,
      15.34,
      15.34,
      15.5,
      15.5,
      15.52,
      15.51,
      15.51,
      15.51,
      15.51,
      15.51,
      15.52,
      15.52,
      15.42,
      15.41
    ],
    "daily": [
      15.18
    ],
    "monthly": [],
    "yearly": []
  },
  "BGN": {
    "hourly": [
      26.85,
      26.85,
      26.85,
      26.85,
      26.85,
      26.85,
      26.85,
      26.85,
      26.85,
      26.85,
      26.85,
      26.85,
      26.85,
      26.85,
      26.85,
      26.85,
      26.85,
      27.05,
      27.05,
      27.05,
      27.05,
      27.05,
      27.05,
      27.05
    ],
    "daily": [
      26.5
    ],
    "monthly": [],
    "yearly": []
  }
}